cybershuttle_sdk/__init__.py
cybershuttle_sdk/auth/__init__.py
cybershuttle_sdk/auth/auth_stubs_pb2.py
cybershuttle_sdk/auth/auth_stubs_pb2_grpc.py
cybershuttle_sdk/execution/__init__.py
cybershuttle_sdk/execution/experiment_service_pb2.py
cybershuttle_sdk/execution/experiment_service_pb2_grpc.py
cybershuttle_sdk/execution/experiment_stub_pb2.py
cybershuttle_sdk/execution/experiment_stub_pb2_grpc.py
cybershuttle_sdk/gateway/__init__.py
cybershuttle_sdk/gateway/gateway_service_pb2.py
cybershuttle_sdk/gateway/gateway_service_pb2_grpc.py
cybershuttle_sdk/gateway/gateway_stubs_pb2.py
cybershuttle_sdk/gateway/gateway_stubs_pb2_grpc.py
cybershuttle_sdk/notification/__init__.py
cybershuttle_sdk/notification/notification_service_pb2.py
cybershuttle_sdk/notification/notification_service_pb2_grpc.py
cybershuttle_sdk/notification/notification_stubs_pb2.py
cybershuttle_sdk/notification/notification_stubs_pb2_grpc.py
cybershuttle_sdk-0.0.1a4.dist-info/LICENSE
cybershuttle_sdk-0.0.1a4.dist-info/METADATA
cybershuttle_sdk-0.0.1a4.dist-info/WHEEL
cybershuttle_sdk-0.0.1a4.dist-info/top_level.txt
cybershuttle_sdk-0.0.1a4.dist-info/RECORD
